{
   "badge" : {

      "badge" : {

         "margin" : 2,
         "fontFamily" : "helvetica",
         "border" : "1px solid #F7F5F1"

      },
      "type" : {

         "service" : {

            "fontSize" : 13,
            "width" : "100%",
            "textAlign" : "left"

         },
         "other" : {

            "width" : "auto",
            "textAlign" : "center"

         }
         
      }

   },
   "board" : {

      "div" : {

         "position" : "relative"

      },
      "dashPlayer" : {
         
         "margin" : "0 0 -5px 0"

      },
      "row" : {

         "top" : 0,
         "margin" : 0,
         "width" : "100%",
         "padding" : "5px",
         "position" : "absolute"

      },
      "col" : {

         "margin" : 0,
         "padding" : 0,
         "overflow" : "auto",
         "overflow-y" : "scroll",
         "overflow-x" : "hidden",
         "scrollbar-width" : "thin"

      },
      "titleH1" : {

         "margin" : 0,
         "fontSize" : 36,
         "fontFamily" : "helvetica",
         "padding" : "3px 0px 1px 9px"

      },
      "contentMarkdown" : {

         "fontSize" : 15,
         "textAlign" : "justify",
         "margin" : "0 0 -13px 0",
         "fontFamily" : "helvetica",
         "padding" : "4px 10px 1px 9px"

      },
      "ecosystemDiv" : {

         "padding" : "7px 8px 8px 8px",
         "margin" : "-13px 0px 0px 0px"

      }

   }
}